setup.cfg
setup.py
assert_tools/__init__.py
assert_tools.egg-info/PKG-INFO
assert_tools.egg-info/SOURCES.txt
assert_tools.egg-info/dependency_links.txt
assert_tools.egg-info/requires.txt
assert_tools.egg-info/top_level.txt
assert_tools/rest/__init__.py
assert_tools/rest/response_json.py
tests/__init__.py
tests/test_functional.py
tests/test_make_api_call.py
tests/test_make_http_response.py
tests/test_make_http_response_from_dict.py
tests/test_response_assertion.py
tests/util.py