Metadata-Version: 1.1
Name: assert-tools
Version: 0.0.2
Summary: A Python Unit/Functional test library.
Home-page: http://mideo.github.io/assert_tools/
Author: Mide Ojikutu
Author-email: mide.ojikutu@gmail.com
License: UNKNOWN
Keywords: testing,python,rest,unit testing,functional testing
Platform: UNKNOWN
Classifier: Topic :: Software Development :: Testing
Classifier: Natural Language :: English
Classifier: Intended Audience :: Developers
Classifier: Development Status :: 5 - Production/Stable
Classifier: Programming Language :: Python :: 2 :: Only
Classifier: License :: OSI Approved :: GNU General Public License v3 (GPLv3)
Classifier: Operating System :: MacOS :: MacOS X
Classifier: Operating System :: Unix
Classifier: Operating System :: POSIX
